{"source_id": 68, "common_name": "HESS J1427-608", "gamma_names": "", "fermi_names": "", "other_names": "Suzaku J1427-6051", "where": "gal", "classes": "unid", "discoverer": "hess", "seen_by": "hess", "discovery_date": "2007-07", "tevcat_id": 139, "tevcat2_id": "eee9un", "tevcat_name": "TeV J1427-608", "tgevcat_id": 68, "tgevcat_name": "TeV J1427-6051", "reference_id": "2008A&A...477..353A", "significance": 7.300000190734863, "livetime": 21.0, "ra": 216.9666748046875, "dec": -60.849998474121094, "glon": 314.4076843261719, "glat": -0.1450013965368271, "pos_ra": 216.9691925048828, "pos_dec": -60.849517822265625, "pos_glon": 314.40899658203125, "pos_glat": -0.14499999582767487, "pos_err": 0.05000000074505806, "morph_type": "gauss", "morph_sigma": 0.03999999910593033, "morph_sigma_err": 0.019999999552965164, "morph_sigma2": 0.07999999821186066, "morph_sigma2_err": 0.019999999552965164, "morph_pa": 80.0, "morph_pa_err": 17.0, "morph_pa_frame": "radec", "spec_type": "pl", "spec_pl_norm": 1.3000000381735433e-12, "spec_pl_norm_err": 3.99999992980668e-13, "spec_pl_norm_err_sys": 1.99999996490334e-13, "spec_pl_index": 2.1600000858306885, "spec_pl_index_err": 0.14000000059604645, "spec_pl_index_err_sys": 0.20000000298023224, "spec_pl_e_ref": 1.0, "spec_pl2_flux": null, "spec_pl2_flux_err": null, "spec_pl2_flux_err_sys": null, "spec_pl2_index": null, "spec_pl2_index_err": null, "spec_pl2_index_err_sys": null, "spec_pl2_e_min": null, "spec_pl2_e_max": null, "spec_ecpl_norm": null, "spec_ecpl_norm_err": null, "spec_ecpl_norm_err_sys": null, "spec_ecpl_index": null, "spec_ecpl_index_err": null, "spec_ecpl_index_err_sys": null, "spec_ecpl_e_cut": null, "spec_ecpl_e_cut_err": null, "spec_ecpl_e_cut_err_sys": null, "spec_ecpl_e_ref": null, "spec_erange_min": 0.9700000286102295, "spec_erange_max": 50.0, "spec_theta": 0.20000000298023224, "spec_dnde_1TeV": 1.3000000381735433e-12, "spec_dnde_1TeV_err": 3.99999992980668e-13, "spec_flux_1TeV": 1.1206894787174626e-12, "spec_flux_1TeV_err": 3.7040525811479763e-13, "spec_flux_1TeV_crab": 5.40236234664917, "spec_flux_1TeV_crab_err": 1.7855645418167114, "spec_eflux_1TeV_10TeV": 4.011647351115366e-12, "spec_eflux_1TeV_10TeV_err": 1.375522308902366e-12, "sed_reference_id": "2008A&A...477..353A", "sed_n_points": 8, "sed_n_ul": 0, "sed_e_ref": [1.2460800409317017, 1.9805200099945068, 3.1933701038360596, 5.139019966125488, 8.278070449829102, 13.334500312805176, 21.47960090637207, 34.59989929199219, null, null, null, null, null, null, null, null, null, null, null, null, null, null, null, null, null, null, null, null, null, null, null, null, null, null, null, null, null, null, null, null], "sed_e_min": [null, null, null, null, null, null, null, null, null, null, null, null, null, null, null, null, null, null, null, null, null, null, null, null, null, null, null, null, null, null, null, null, null, null, null, null, null, null, null, null], "sed_e_max": [null, null, null, null, null, null, null, null, null, null, null, null, null, null, null, null, null, null, null, null, null, null, null, null, null, null, null, null, null, null, null, null, null, null, null, null, null, null, null, null], "sed_dnde": [5.307130060937248e-13, 3.5982398701242535e-13, 1.0125299714338135e-13, 3.8036400743478305e-14, 2.4383300283384313e-14, 2.9848799433784e-15, 1.2601999488154238e-15, 6.325240238840761e-16, null, null, null, null, null, null, null, null, null, null, null, null, null, null, null, null, null, null, null, null, null, null, null, null, null, null, null, null, null, null, null, null], "sed_dnde_err": [null, null, null, null, null, null, null, null, null, null, null, null, null, null, null, null, null, null, null, null, null, null, null, null, null, null, null, null, null, null, null, null, null, null, null, null, null, null, null, null], "sed_dnde_errp": [3.4753900061620935e-13, 1.1258400082429093e-13, 3.90440989001678e-14, 1.4747900708815542e-14, 6.961720171286311e-15, 2.376840095048979e-15, 9.695920502166564e-16, 4.3017701132876595e-16, null, null, null, null, null, null, null, null, null, null, null, null, null, null, null, null, null, null, null, null, null, null, null, null, null, null, null, null, null, null, null, null], "sed_dnde_errn": [3.33892988127818e-13, 1.0741699820208603e-13, 3.665490017090191e-14, 1.3626999986857298e-14, 6.3579199346161346e-15, 2.0702400026478135e-15, 7.955590197474525e-16, 3.269759993429597e-16, null, null, null, null, null, null, null, null, null, null, null, null, null, null, null, null, null, null, null, null, null, null, null, null, null, null, null, null, null, null, null, null], "sed_dnde_ul": [null, null, null, null, null, null, null, null, null, null, null, null, null, null, null, null, null, null, null, null, null, null, null, null, null, null, null, null, null, null, null, null, null, null, null, null, null, null, null, null], "catalog_row_index": 68}